README.md
setup.py
sample_package/__init__.py
sample_package/sample.py
szuwar_hello_world.egg-info/PKG-INFO
szuwar_hello_world.egg-info/SOURCES.txt
szuwar_hello_world.egg-info/dependency_links.txt
szuwar_hello_world.egg-info/top_level.txt